setup.py
django_mandrill/__init__.py
django_mandrill/models.py
django_mandrill/tests.py
django_mandrill/views.py
django_mandrill.egg-info/PKG-INFO
django_mandrill.egg-info/SOURCES.txt
django_mandrill.egg-info/dependency_links.txt
django_mandrill.egg-info/requires.txt
django_mandrill.egg-info/top_level.txt
django_mandrill/mail/__init__.py
django_mandrill/mail/mandrillmail.py
django_mandrill/mail/backends/__init__.py
django_mandrill/mail/backends/mandrillbackend.py