Metadata-Version: 1.1
Name: django-mandrill
Version: 0.1.0
Summary: Mandrill integration for Django
Home-page: https://bitbucket.org/sirpengi/django-mandrill
Author: Shu Zong Chen
Author-email: shu.chen@freelancedreams.com
License: MIT License
Download-URL: https://bitbucket.org/sirpengi/django-mandrill/downloads
Keywords: django mandrill email email-backend
Platform: any
Classifier: Development Status :: 5 - Production/Stable
Classifier: Environment :: Web Environment
Classifier: Framework :: Django
Classifier: Intended Audience :: Developers
Classifier: License :: OSI Approved :: MIT License
Classifier: Operating System :: OS Independent
Classifier: Programming Language :: Python
Classifier: Topic :: Software Development :: Libraries :: Application Frameworks
Classifier: Topic :: Software Development :: Libraries :: Python Modules
